html2img/__init__.py
html2img/test.py
html2img-0.1.0.dist-info/METADATA
html2img-0.1.0.dist-info/WHEEL
html2img-0.1.0.dist-info/top_level.txt
html2img-0.1.0.dist-info/RECORD
